<?xml version="1.0"?>
<monster name="Dworc Venomsniper" level="5" maglevel="5" experience="30" pushable="0" speed="152"  armor="3" defense="5" canpushitems="0" staticattack="50" changetarget="200">
	<health now="80" max="80"/>
	<look type="216" corpse="4310"/>
	<combat targetdistance="1" runonhealth="0"/>
<attacks>
	<attack type="melee" maxdamage="30" cycleticks="2000" probability="100"/>	
	<attack type="distance" name="poisonfield" mindamage="0" maxdamage="10"/>

</attacks>

<defenses>
<defense immunity="poison"/>
<defense immunity="drunk"/>
</defenses>

<loot>
</loot>
<voices>
	<voice sentence="Grak brrretz!"/>
	<voice sentence="Grow truk grrrrr"/>
	<voice sentence="Prek tars, dekklep zurk"/>
</voices>

</monster>
